{
	"pages": [ //pages数组中第一项表示应用启动页，参考：https://uniapp.dcloud.io/collocation/pages
		{
			"path" : "pages/login/login",
			"style" : 
			{
				"navigationStyle": "custom",
				"navigationBarTitleText": "登录"
			}
		},
		{
			"path" : "pages/doctorIndex/doctorIndex",
			"style" : 
			{
				"navigationStyle": "custom"
			}
		},
		{
			"path" : "pages/administerIndex/administerIndex",
			"style" : 
			{
				"navigationStyle": "custom"
			}
		},
		{
			"path" : "pages/clinicIndex/clinicIndex",
			"style" : 
			{
				"navigationStyle": "custom"
			}
		},
		{
			"path" : "pages/doctorPerson/doctorPerson",
			"style" : 
			{
				"navigationStyle": "custom"
			}
		},
		{
			"path" : "pages/administerPerson/administerPerson",
			"style" : 
			{
				"navigationStyle": "custom"
			}
		},
		{
			"path" : "pages/clinicPerson/clinicPerson",
			"style" : 
			{
				"navigationStyle": "custom"
			}
		}
	],
	"globalStyle": {
		"navigationBarTextStyle": "black",
		"navigationBarBackgroundColor": "#F8F8F8",
		"backgroundColor": "#F8F8F8"
	},
	"uniIdRouter": {}
}
